sensorsabtesting/__init__.py
sensorsabtesting/ab_const.py
sensorsabtesting/abtest.py
sensorsabtesting/unit_test_ab.py
sensorsabtesting/cache/__init__.py
sensorsabtesting/cache/func.py
sensorsabtesting/cache/keys.py
SensorsABTestingSDK-0.0.3.dist-info/LICENSE
SensorsABTestingSDK-0.0.3.dist-info/METADATA
SensorsABTestingSDK-0.0.3.dist-info/WHEEL
SensorsABTestingSDK-0.0.3.dist-info/top_level.txt
SensorsABTestingSDK-0.0.3.dist-info/RECORD
