Metadata-Version: 2.1
Name: SensorsABTestingSDK
Version: 0.0.3
Summary: This is the official Python ABTesting SDK for Sensors Analytics.
Home-page: https://github.com/sensorsdata/abtesting-sdk-python
Author: Jianzhong YUE
Author-email: yuejianzhong@sensorsdata.cn
License: UNKNOWN
Platform: UNKNOWN
Requires-Dist: SensorsAnalyticsSDK
Requires-Dist: urllib3 (==1.26.9)
